LICENSE
README.md
pyproject.toml
setup.cfg
setup.py
src/zenodopy/__init__.py
src/zenodopy/py.typed
src/zenodopy/zenodopy.py
src/zenodopy.egg-info/PKG-INFO
src/zenodopy.egg-info/SOURCES.txt
src/zenodopy.egg-info/dependency_links.txt
src/zenodopy.egg-info/not-zip-safe
src/zenodopy.egg-info/requires.txt
src/zenodopy.egg-info/top_level.txt