Metadata-Version: 2.1
Name: zenodopy
Version: 0.3.0
Summary: manage zenodo project
Home-page: https://github.com/lgloege/zenodopy
Author: Luke Gloege
Author-email: ljg2157@columbia.edu
License: MIT
Keywords: zenodo
Platform: unix
Platform: linux
Platform: osx
Platform: cygwin
Platform: win32
Classifier: Development Status :: 3 - Alpha
Classifier: Intended Audience :: Developers
Classifier: Topic :: Software Development :: Build Tools
Classifier: License :: OSI Approved :: MIT License
Classifier: Programming Language :: Python :: 3
Classifier: Programming Language :: Python :: 3 :: Only
Classifier: Programming Language :: Python :: 3.6
Classifier: Programming Language :: Python :: 3.7
Classifier: Programming Language :: Python :: 3.8
Classifier: Programming Language :: Python :: 3.9
Requires-Python: >=3.6
Provides-Extra: testing
License-File: LICENSE
